{
  "金属": {
    "スクラップ": 20,
    "閃亜鉛鉱": 65,
    "鉄鉱石": 70,
    "黄銅鋼": 80,
    "方鉛鉱": 85,
    "クロム": 100,
    "錫石": 150,
    "ハイメタル": 180,
    "メテオライト": 500,
    "ミスリル": 1000
  },
  "植物": {
    "薬草": 5,
    "チドメグサ": 8,
    "解毒草": 15,
    "綿花": 60,
    "ケシの未果実": 90,
    "ゴムの樹液": 100,
    "竜血樹": 150,
    "封印木": 300,
    "仙人掌の花": 500,
    "リグナムバイタ": 1000
  },
  "獣": {
    "獣骨": 5,
    "毛皮": 8,
    "獣肉": 10,
    "獣脂": 100,
    "美しい羽": 120,
    "牙": 150,
    "胆汁": 250,
    "丈夫な筋": 300,
    "甲皮": 500,
    "一本角": 1000
  },
  "食品": {
    "チーズ": 3,
    "林檎": 5,
    "玉ねぎ": 8,
    "ワイン": 10,
    "ライ麦": 15,
    "小麦": 30,
    "オリーブ油": 40,
    "葡萄": 100,
    "岩塩": 250,
    "胡椒": 1000
  },
  "宝石": {
    "コーラル": 500,
    "ジャスパー": 800,
    "サファイア": 1000,
    "ルビー": 1500,
    "水晶": 2000,
    "真珠": 2500,
    "魔光石": 5000,
    "エメラルド": 6500,
    "オパール": 8000,
    "ダイヤモンド": 10000
  },
  "その他": {
    "粘土": 10,
    "シーグラス": 20,
    "木炭": 25,
    "歯車": 50,
    "魔法石": 100,
    "火薬": 200,
    "壺": 500,
    "生き血": 1000,
    "麻の生地": 2000,
    "シルクの生地": 8000
  }
}